LICENSE
README.md
pyproject.toml
torchdt/__init__.py
torchdt/_build_ext.py
torchdt/autograd.py
torchdt/datatype.py
torchdt/transforms.py
torchdt.egg-info/PKG-INFO
torchdt.egg-info/SOURCES.txt
torchdt.egg-info/dependency_links.txt
torchdt.egg-info/requires.txt
torchdt.egg-info/top_level.txt
torchdt/csrc/dispatcher.h
torchdt/csrc/extension.cpp
torchdt/csrc/lns16.cpp
torchdt/csrc/lns16.h
torchdt/csrc/ops_impl.cpp
torchdt/csrc/ops_impl.h
torchdt/funcs/__init__.py
torchdt/funcs/activation_funcs.py
torchdt/funcs/arithmetic_funcs.py
torchdt/funcs/comparison_funcs.py
torchdt/funcs/creation_funcs.py
torchdt/funcs/init_funcs.py
torchdt/funcs/layer_funcs.py
torchdt/funcs/loss_funcs.py
torchdt/funcs/misc_funcs.py
torchdt/funcs/unary_funcs.py
torchdt/include/torchdt/registry.h
torchdt/lns/__init__.py
torchdt/lns/lns16.py
torchdt/lns/lns32.py
torchdt/lns/lns64.py
torchdt/ops/__init__.py
torchdt/ops/activation_ops.py
torchdt/ops/arithmetic_ops.py
torchdt/ops/base.py
torchdt/ops/comparison_ops.py
torchdt/ops/cpp_ops.py
torchdt/ops/layer_ops.py
torchdt/ops/loss_ops.py
torchdt/ops/misc_ops.py
torchdt/ops/triton_ops.py
torchdt/ops/unary_ops.py
torchdt/optim/__init__.py
torchdt/optim/adam.py
torchdt/optim/lr_scheduler.py
torchdt/optim/madam.py
torchdt/optim/optimizer.py
torchdt/optim/sgd.py