Metadata-Version: 2.4
Name: torchdt
Version: 0.1.0
Summary: torchdt is a python package that provides custom datatypes for training and inference in PyTorch.
Author-email: Alexander Krentz <alexkrentz2@gmail.com>
License: MIT License
Project-URL: Homepage, https://github.com/akrentz6/torchdt
Keywords: python,pytorch,machine learning
License-File: LICENSE
Requires-Dist: torch>=2.0
Requires-Dist: numpy
Dynamic: license-file
